ai_test_agent/__init__.py
ai_test_agent/agent/__init__.py
ai_test_agent/agent/agent.py
ai_test_agent/agent/prompts.py
ai_test_agent/agent/tools.py
ai_test_agent/cli.py
ai_test_agent/config.py
ai_test_agent/executor/__init__.py
ai_test_agent/executor/environment.py
ai_test_agent/executor/test_runner.py
ai_test_agent/explorer/__init__.py
ai_test_agent/explorer/analyzer.py
ai_test_agent/explorer/file_tools.py
ai_test_agent/explorer/parser.py
ai_test_agent/generator/__init__.py
ai_test_agent/generator/data_generator.py
ai_test_agent/generator/templates/html_report.j2
ai_test_agent/generator/templates/java_test.j2
ai_test_agent/generator/templates/javascript_test.j2
ai_test_agent/generator/templates/python_test.j2
ai_test_agent/generator/test_generator.py
ai_test_agent/main.py
ai_test_agent/reporting/__init__.py
ai_test_agent/reporting/aggregator.py
ai_test_agent/reporting/coverage.py
ai_test_agent/reporting/reporter.py
ai_test_agent-0.1.0.dist-info/METADATA
ai_test_agent-0.1.0.dist-info/WHEEL
ai_test_agent-0.1.0.dist-info/entry_points.txt
ai_test_agent-0.1.0.dist-info/licenses/LICENSE
ai_test_agent-0.1.0.dist-info/RECORD
