Metadata-Version: 2.4
Name: ai-test-agent
Version: 0.1.0
Summary: AI-powered test automation agent
License-File: LICENSE
Author: Your Name
Author-email: your.email@example.com
Requires-Python: >=3.12,<4.0
Classifier: Programming Language :: Python :: 3
Classifier: Programming Language :: Python :: 3.12
Classifier: Programming Language :: Python :: 3.13
Classifier: Programming Language :: Python :: 3.14
Requires-Dist: aiofiles (>=23.2.1,<24.0.0)
Requires-Dist: click (>=8.1.7,<9.0.0)
Requires-Dist: coverage (>=7.3.2,<8.0.0)
Requires-Dist: jinja2 (>=3.1.2,<4.0.0)
Requires-Dist: langchain (>=1.0.0,<2.0.0)
Requires-Dist: langchain-community (>=0.4.0,<0.5.0)
Requires-Dist: langchain-core (>=1.0.0,<2.0.0)
Requires-Dist: langgraph (>=1.0.0,<2.0.0)
Requires-Dist: networkx (>=3.2.1,<4.0.0)
Requires-Dist: ollama (>=0.1.7,<0.2.0)
Requires-Dist: playwright (>=1.40.0,<2.0.0)
Requires-Dist: pydantic (>=2.4.2,<3.0.0)
Requires-Dist: pydantic-settings (>=2.0.0,<3.0.0)
Requires-Dist: pytest (>=7.4.3,<8.0.0)
Requires-Dist: pytest-asyncio (>=0.21.1,<0.22.0)
Requires-Dist: rich (>=13.6.0,<14.0.0)
Requires-Dist: scipy (>=1.16.2,<2.0.0)
Requires-Dist: tree-sitter (>=0.25.0,<0.26.0)
Requires-Dist: tree-sitter-java (>=0.23.5,<0.24.0)
Requires-Dist: tree-sitter-javascript (>=0.25.0,<0.26.0)
Requires-Dist: tree-sitter-python (>=0.25.0,<0.26.0)
